dagster_sharepoint/__init__.py
dagster_sharepoint/resource.py
dagster_sharepoint-0.0.2.dist-info/METADATA
dagster_sharepoint-0.0.2.dist-info/WHEEL
dagster_sharepoint-0.0.2.dist-info/top_level.txt
dagster_sharepoint-0.0.2.dist-info/RECORD
