Metadata-Version: 2.4
Name: dagster-sharepoint
Version: 0.0.2
Summary: Dagster integration for SharePoint document management using Microsoft Graph API
Requires-Python: >=3.10
Requires-Dist: dagster>=1.8.0
Requires-Dist: requests>=2.31.0
